Flask_SQLalchemy_Whoosh/__init__.py
Flask_SQLalchemy_Whoosh/mixin.py
Flask_SQLalchemy_Whoosh/searcher.py
flask_sqlalchemy_whoosh-0.1.5.dist-info/METADATA
flask_sqlalchemy_whoosh-0.1.5.dist-info/WHEEL
flask_sqlalchemy_whoosh-0.1.5.dist-info/licenses/LICENSE
flask_sqlalchemy_whoosh-0.1.5.dist-info/RECORD
